cronex/tests.py
cronex/__init__.py
cronex-0.1.1.dist-info/WHEEL
cronex-0.1.1.dist-info/metadata.json
cronex-0.1.1.dist-info/METADATA
cronex-0.1.1.dist-info/top_level.txt
cronex-0.1.1.dist-info/RECORD
cronex-0.1.1.dist-info/DESCRIPTION.rst
