Metadata-Version: 2.0
Name: cronex
Version: 0.1.1
Summary: This module provides an easy to use interface for cron-like task scheduling.
Home-page: https://github.com/ericpruitt/cronex
Author: Eric Pruitt
Author-email: eric.pruitt@gmail.com
License: MIT
Keywords: cron,scheduler,triggers,time,quartz
Platform: UNKNOWN
Classifier: License :: OSI Approved :: MIT License
Classifier: Operating System :: POSIX
Classifier: Programming Language :: Python :: 2
Classifier: Programming Language :: Python :: 2.4
Classifier: Programming Language :: Python :: 2.5
Classifier: Programming Language :: Python :: 2.6
Classifier: Programming Language :: Python :: 2.7
Classifier: Programming Language :: Python :: 3
